[
  {
    "ref": "Chequia|Sudáfrica::ta_local",
    "match_id": 3,
    "local": "Chequia",
    "visitante": "Sudáfrica",
    "campo": "ta_local",
    "valor_wiki": 0,
    "valor_scraper": 1,
    "detectado": "2026-07-01T05:08:08+00:00"
  },
  {
    "ref": "Chequia|Sudáfrica::ta_visit",
    "match_id": 3,
    "local": "Chequia",
    "visitante": "Sudáfrica",
    "campo": "ta_visit",
    "valor_wiki": 0,
    "valor_scraper": 2,
    "detectado": "2026-07-01T05:08:08+00:00"
  },
  {
    "ref": "Paraguay|Turquía::ta_local",
    "match_id": 22,
    "local": "Turquía",
    "visitante": "Paraguay",
    "campo": "ta_local",
    "valor_wiki": 2,
    "valor_scraper": 1,
    "detectado": "2026-07-01T05:08:08+00:00"
  },
  {
    "ref": "Paraguay|Turquía::ta_visit",
    "match_id": 22,
    "local": "Turquía",
    "visitante": "Paraguay",
    "campo": "ta_visit",
    "valor_wiki": 2,
    "valor_scraper": 1,
    "detectado": "2026-07-01T05:08:08+00:00"
  },
  {
    "ref": "Alemania|Ecuador::ta_local",
    "match_id": 29,
    "local": "Ecuador",
    "visitante": "Alemania",
    "campo": "ta_local",
    "valor_wiki": 0,
    "valor_scraper": 3,
    "detectado": "2026-07-01T05:08:08+00:00"
  },
  {
    "ref": "Alemania|Ecuador::ta_visit",
    "match_id": 29,
    "local": "Ecuador",
    "visitante": "Alemania",
    "campo": "ta_visit",
    "valor_wiki": 0,
    "valor_scraper": 1,
    "detectado": "2026-07-01T05:08:08+00:00"
  },
  {
    "ref": "Egipto|Irán::gf_local",
    "match_id": 42,
    "local": "Egipto",
    "visitante": "Irán",
    "campo": "gf_local",
    "valor_wiki": null,
    "valor_scraper": 1,
    "detectado": "2026-07-01T05:08:08+00:00"
  },
  {
    "ref": "Egipto|Irán::gf_visit",
    "match_id": 42,
    "local": "Egipto",
    "visitante": "Irán",
    "campo": "gf_visit",
    "valor_wiki": null,
    "valor_scraper": 1,
    "detectado": "2026-07-01T05:08:08+00:00"
  },
  {
    "ref": "Alemania|Paraguay::ta_local",
    "match_id": 75,
    "local": "Alemania",
    "visitante": "Paraguay",
    "campo": "ta_local",
    "valor_wiki": 4,
    "valor_scraper": 2,
    "detectado": "2026-07-01T05:08:08+00:00"
  },
  {
    "ref": "Alemania|Paraguay::ta_visit",
    "match_id": 75,
    "local": "Alemania",
    "visitante": "Paraguay",
    "campo": "ta_visit",
    "valor_wiki": 4,
    "valor_scraper": 2,
    "detectado": "2026-07-01T05:08:08+00:00"
  },
  {
    "ref": "Ecuador|México::gf_local",
    "match_id": 79,
    "local": "México",
    "visitante": "Ecuador",
    "campo": "gf_local",
    "valor_wiki": null,
    "valor_scraper": 2,
    "detectado": "2026-07-01T05:08:08+00:00"
  },
  {
    "ref": "Ecuador|México::gf_visit",
    "match_id": 79,
    "local": "México",
    "visitante": "Ecuador",
    "campo": "gf_visit",
    "valor_wiki": null,
    "valor_scraper": 0,
    "detectado": "2026-07-01T05:08:08+00:00"
  },
  {
    "ref": "Ecuador|México::ta_visit",
    "match_id": 79,
    "local": "México",
    "visitante": "Ecuador",
    "campo": "ta_visit",
    "valor_wiki": 0,
    "valor_scraper": 3,
    "detectado": "2026-07-01T05:08:08+00:00"
  },
  {
    "ref": "Ecuador|México::rd_visit",
    "match_id": 79,
    "local": "México",
    "visitante": "Ecuador",
    "campo": "rd_visit",
    "valor_wiki": 0,
    "valor_scraper": 1,
    "detectado": "2026-07-01T05:08:08+00:00"
  }
]